scGeneFit/__init__.py
scGeneFit/functions.py
scGeneFit/data_files/CITEseq-labels.mat
scGeneFit/data_files/CITEseq.mat
scGeneFit/data_files/CITEseq_names.mat
scGeneFit/data_files/__init__.py
scGeneFit/data_files/zeisel_data.mat
scGeneFit/data_files/zeisel_labels1.mat
scGeneFit/data_files/zeisel_labels2.mat
scGeneFit/data_files/zeisel_names.mat
scGeneFit-1.0.2.dist-info/LICENSE
scGeneFit-1.0.2.dist-info/METADATA
scGeneFit-1.0.2.dist-info/WHEEL
scGeneFit-1.0.2.dist-info/top_level.txt
scGeneFit-1.0.2.dist-info/RECORD
