Metadata-Version: 2.1
Name: scGeneFit
Version: 1.0.2
Summary: Genetic marker selection with linear programming
Home-page: https://github.com/solevillar/scGeneFit-python
Author: Soledad Villar
Author-email: soledad.villar@nyu.edu
License: UNKNOWN
Platform: UNKNOWN
Classifier: Programming Language :: Python :: 3
Classifier: License :: OSI Approved :: MIT License
Classifier: Operating System :: OS Independent
Requires-Python: >=3.6
Requires-Dist: numpy
Requires-Dist: matplotlib
Requires-Dist: scipy
Requires-Dist: sklearn
